vexbi/__init__.py
vexbi/api.py
vexbi/base.py
vexbi/client.py
vexbi/config.py
vexbi/response.py
vexbi/api_auth/__init__.py
vexbi/api_auth/api_auth.py
vexbi/api_auth/context_manager.py
vexbi/api_auth/requests_api_auth.py
vexbi/api_auth/signature.py
vexbi-0.0.1.dist-info/LICENSE.txt
vexbi-0.0.1.dist-info/METADATA
vexbi-0.0.1.dist-info/WHEEL
vexbi-0.0.1.dist-info/top_level.txt
vexbi-0.0.1.dist-info/RECORD
