Metadata-Version: 2.1
Name: vexbi
Version: 0.0.1
Summary: Python API Client library for Vexbi.com
Home-page: https://github.com/vexbiexchange/python-api-client
Author: Jaime Victoria
Author-email: jaime@michelada.io
License: MIT
Download-URL: https://github.com/vexbiexchange/python-api-client/tarball/v0.0.6
Platform: UNKNOWN
Requires-Dist: requests
